aiojira/__init__.py
aiojira/__init__.pyi
aiojira/resilientsession.pyi
aiojira-0.1.14.dist-info/LICENSE
aiojira-0.1.14.dist-info/WHEEL
aiojira-0.1.14.dist-info/METADATA
aiojira-0.1.14.dist-info/RECORD
