Metadata-Version: 2.1
Name: aiojira
Version: 0.1.14
Summary: Asynchronous Jira library
Home-page: https://github.com/rominf/aiojira
License: Apache-2.0
Keywords: jira,async,asyncio
Author: Roman Inflianskas
Author-email: r.inflyanskas@zmeke.com
Requires-Python: >=3.6,<4.0
Classifier: License :: OSI Approved :: Apache Software License
Classifier: Programming Language :: Python :: 3
Classifier: Programming Language :: Python :: 3.6
Classifier: Programming Language :: Python :: 3.7
Classifier: Topic :: Software Development :: Libraries :: Python Modules
Requires-Dist: aioify (>=0.3.1,<0.4.0)
Requires-Dist: jira (>=2.0,<3.0)
Requires-Dist: poetry-version (>=0.1.2,<0.2.0)
Project-URL: Repository, https://github.com/rominf/aiojira
